README.txt
setup.cfg
setup.py
docs/HISTORY.txt
docs/INSTALL.txt
docs/LICENSE.GPL
docs/LICENSE.txt
easyshop/__init__.py
easyshop.criteria.egg-info/PKG-INFO
easyshop.criteria.egg-info/SOURCES.txt
easyshop.criteria.egg-info/dependency_links.txt
easyshop.criteria.egg-info/entry_points.txt
easyshop.criteria.egg-info/namespace_packages.txt
easyshop.criteria.egg-info/not-zip-safe
easyshop.criteria.egg-info/requires.txt
easyshop.criteria.egg-info/top_level.txt
easyshop/criteria/__init__.py
easyshop/criteria/configure.zcml
easyshop/criteria/profiles.zcml
easyshop/criteria/tests.py
easyshop/criteria/adapters/__init__.py
easyshop/criteria/adapters/category.py
easyshop/criteria/adapters/configure.zcml
easyshop/criteria/adapters/country.py
easyshop/criteria/adapters/customer.py
easyshop/criteria/adapters/date.py
easyshop/criteria/adapters/group.py
easyshop/criteria/adapters/payment_method.py
easyshop/criteria/adapters/price.py
easyshop/criteria/adapters/product.py
easyshop/criteria/adapters/product_amount.py
easyshop/criteria/adapters/shipping_method.py
easyshop/criteria/adapters/stock_amount.py
easyshop/criteria/adapters/weight.py
easyshop/criteria/content/__init__.py
easyshop/criteria/content/category.py
easyshop/criteria/content/country.py
easyshop/criteria/content/customer.py
easyshop/criteria/content/date.py
easyshop/criteria/content/group.py
easyshop/criteria/content/payment_method.py
easyshop/criteria/content/price.py
easyshop/criteria/content/product.py
easyshop/criteria/content/product_amount.py
easyshop/criteria/content/shipping_method.py
easyshop/criteria/content/stock_amount.py
easyshop/criteria/content/weight.py
easyshop/criteria/profiles/default/factorytool.xml
easyshop/criteria/profiles/default/types.xml
easyshop/criteria/profiles/default/workflows.xml
easyshop/criteria/profiles/default/types/CategoryCriteria.xml
easyshop/criteria/profiles/default/types/CountryCriteria.xml
easyshop/criteria/profiles/default/types/CustomerCriteria.xml
easyshop/criteria/profiles/default/types/DateCriteria.xml
easyshop/criteria/profiles/default/types/GroupCriteria.xml
easyshop/criteria/profiles/default/types/PaymentMethodCriteria.xml
easyshop/criteria/profiles/default/types/PriceCriteria.xml
easyshop/criteria/profiles/default/types/ProductAmountCriteria.xml
